aws_obp_1/__init__.py
aws_obp_1/auto_scaling.py
aws_obp_1/ec2.py
aws_obp_1/lambda_fn.py
aws_obp_1/lb.py
aws_obp_1/rds.py
aws_obp_1/s3.py
aws_obp_1/utils.py
aws_obp_1-0.1.2.dist-info/METADATA
aws_obp_1-0.1.2.dist-info/WHEEL
aws_obp_1-0.1.2.dist-info/top_level.txt
aws_obp_1-0.1.2.dist-info/RECORD
